DSM/Utils.py
DSM/__init__.py
DSM/metrics.py
DSM/test_format.py
DSM/Ensemble/EMLR.py
DSM/Ensemble/EMNN.py
DSM/Ensemble/__init__.py
DSM/Model_selection/NNSelector.py
DSM/Model_selection/NaiveSelector.py
DSM/Model_selection/SDaysSelector.py
DSM/Model_selection/__init__.py
DSM/models/BaseModel.py
DSM/models/DayFeaturesLR.py
DSM/models/DayFeaturesNN.py
DSM/models/DayFunctions.py
DSM/models/HW.py
DSM/models/RLS.py
DSM/models/SARIMA.py
DSM/models/SDaysAVR.py
DSM/models/STA.py
DSM/models/TDaysAVR.py
DSM/models/__init__.py
DSM/structures/__init__.py
DSM/structures/dsm_timeseries.py
dsm_lib-3.1.0.dist-info/METADATA
dsm_lib-3.1.0.dist-info/WHEEL
dsm_lib-3.1.0.dist-info/top_level.txt
dsm_lib-3.1.0.dist-info/RECORD
