Metadata-Version: 2.1
Name: dsm-lib
Version: 3.1.0
Summary: DSM library for a forecast air pollution
Author: Igor Chernitsin
Requires-Dist: numpy~=1.26.3
Requires-Dist: pandas~=2.1.4
Requires-Dist: scikit-learn~=1.3.2
Requires-Dist: tqdm~=4.66.1
Requires-Dist: setuptools~=68.2.0
Requires-Dist: padasip~=1.2.2
Requires-Dist: keras~=3.4.1
Requires-Dist: tensorflow~=2.16.1
Requires-Dist: statsmodels~=0.14.2
